dns_exporter/__init__.py
dns_exporter/_version.py
dns_exporter/collector.py
dns_exporter/config.py
dns_exporter/dns_exporter_example.yml
dns_exporter/entrypoint.py
dns_exporter/exceptions.py
dns_exporter/exporter.py
dns_exporter/metrics.py
dns_exporter/version.py
dns_exporter-1.1.0.dist-info/LICENSE
dns_exporter-1.1.0.dist-info/METADATA
dns_exporter-1.1.0.dist-info/WHEEL
dns_exporter-1.1.0.dist-info/entry_points.txt
dns_exporter-1.1.0.dist-info/top_level.txt
dns_exporter-1.1.0.dist-info/RECORD
