Metadata-Version: 2.2
Name: dns_exporter
Version: 1.1.0
Summary: Multi-target Prometheus exporter with an exclusive focus on DNS monitoring
Author: Thomas Steen Rasmussen
Author-email: thomas@gibfest.dk
License: BSD 3-Clause License
Project-URL: homepage, https://github.com/tykling/dns_exporter
Project-URL: documentation, https://dns-exporter.readthedocs.org/
Keywords: prometheus,dns,monitoring
Classifier: License :: OSI Approved :: BSD License
Classifier: Programming Language :: Python :: 3
Classifier: Operating System :: OS Independent
Requires-Python: >=3.10
License-File: LICENSE
Requires-Dist: dnspython[dnssec,doh,doq,idna]>=2.7.0
Requires-Dist: PyYAML>=6.0
Requires-Dist: prometheus-client>=0.15.0
Requires-Dist: PySocks>=1.7.1
Provides-Extra: dev
Requires-Dist: pre-commit==4.1.0; extra == "dev"
Requires-Dist: setuptools-scm==8.1.0; extra == "dev"
Provides-Extra: test
Requires-Dist: coverage[toml]==7.6.12; extra == "test"
Requires-Dist: gera2ld.socks==0.5.0; extra == "test"
Requires-Dist: prometheus-client==0.21.1; extra == "test"
Requires-Dist: pytest==8.3.4; extra == "test"
Requires-Dist: pytest-cov==6.0.0; extra == "test"
Requires-Dist: pytest-mock==3.14.0; extra == "test"
Requires-Dist: pytest-order==1.3.0; extra == "test"
Requires-Dist: pytest-randomly==3.16.0; extra == "test"
Requires-Dist: requests==2.32.3; extra == "test"
Requires-Dist: tox==4.24.1; extra == "test"
Requires-Dist: types-PyYAML==6.0.12.20241230; extra == "test"
Provides-Extra: docs
Requires-Dist: Sphinx==8.1.3; extra == "docs"
Requires-Dist: sphinx_changelog==1.6.0; extra == "docs"
